tpass/__init__.py
tpass/totp.py
tpass-1.0a5.dist-info/LICENSE
tpass-1.0a5.dist-info/METADATA
tpass-1.0a5.dist-info/WHEEL
tpass-1.0a5.dist-info/entry_points.txt
tpass-1.0a5.dist-info/top_level.txt
tpass-1.0a5.dist-info/RECORD
