Metadata-Version: 2.1
Name: tpass
Version: 1.0a5
Summary: A terminal based password manager.
Author-email: Marc Culler <culler@users.noreply.github.com>
Maintainer-email: Marc Culler <culler@users.noreply.github.com>
Project-URL: Homepage, https://github.com/culler/tpass
Project-URL: Bug Tracker, https://github.com/culler/tpass/issues
Keywords: password,manager
Classifier: Development Status :: 3 - Alpha
Classifier: Intended Audience :: End Users/Desktop
Classifier: License :: OSI Approved :: MIT License
Classifier: Operating System :: OS Independent
Classifier: Programming Language :: Python
Classifier: Topic :: Utilities
Requires-Python: >=3.8
License-File: LICENSE
Requires-Dist: chafe
Requires-Dist: tomlkit
